tpd_analyse/__init__.py
tpd_analyse/tpd.py
tpd_analyse-0.2.0.dist-info/LICENSE.txt
tpd_analyse-0.2.0.dist-info/METADATA
tpd_analyse-0.2.0.dist-info/WHEEL
tpd_analyse-0.2.0.dist-info/top_level.txt
tpd_analyse-0.2.0.dist-info/RECORD
