Metadata-Version: 2.1
Name: tpd-analyse
Version: 0.2.0
Summary: A python module of determining adsorption energies from temperature programmed desorption curves
Home-page: UNKNOWN
Author: Sudarshan Vijay
Author-email: vijays@fysik.dtu.dk
License: MIT
Platform: UNKNOWN
Requires-Python: >=3.6
License-File: LICENSE.txt
Requires-Dist: numpy
Requires-Dist: scipy
Requires-Dist: matplotlib
Requires-Dist: mpmath
Requires-Dist: ase
